pybwt/__init__.py
pybwt/bwt_utils.py
pybwt/main.py
pybwt-0.1.2.dist-info/METADATA
pybwt-0.1.2.dist-info/WHEEL
pybwt-0.1.2.dist-info/top_level.txt
pybwt-0.1.2.dist-info/RECORD
