Metadata-Version: 2.1
Name: pybwt
Version: 0.1.2
Summary: UNKNOWN
Home-page: https://github.com/OriSavir/PyBWT
Author: Oriel Savir
License: UNKNOWN
Platform: UNKNOWN
